README.md
setup.py
indented/__init__.py
indented/codegen.py
indented/text.py
indented.egg-info/PKG-INFO
indented.egg-info/SOURCES.txt
indented.egg-info/dependency_links.txt
indented.egg-info/top_level.txt
indented/experimental/__init__.py
indented/experimental/binary_switch.py
indented/tests/__init__.py
indented/tests/test.py