Metadata-Version: 2.1
Name: indented
Version: 0.9.0
Summary: Tools for generating Python code and other indented text.
Home-page: UNKNOWN
Author: J Uryga
Author-email: lolzatu2@gmail.com
License: UNKNOWN
Project-URL: Source, https://github.com/lubieowoce/indented
Keywords: codegen code generation indented macro
Platform: UNKNOWN
